{
    "title": "Button's damp squib: High hopes in Shanghai but Vettelwins in rain",
    "url": "https://www.dailymail.co.uk/sport/formulaone/article-1171912/Buttons-damp-squib-High-hopes-Shanghai-Vettel-wins-rain.html",
    "date": "2009-04-19",
    "keywords": [
        "vettel",
        "button",
        "car",
        "bull",
        "race",
        "rain",
        "prix",
        "team",
        "wet",
        "year",
        "victory",
        "formula",
        "china",
        "share",
        "teammate",
        "webber",
        "time",
        "season",
        "horner",
        "win",
        "hamilton",
        "bmw",
        "place",
        "surprise",
        "shanghai",
        "jonathan",
        "mcevoy",
        "mail",
        "gmt",
        "april",
        "view",
        "perfection",
        "buttonvictory",
        "third",
        "briton",
        "damon",
        "hill",
        "hattrick",
        "winsit",
        "devotee",
        "statement",
        "action",
        "article",
        "flawless",
        "pulsating",
        "pit",
        "pole",
        "mark",
        "championship",
        "lead",
        "brawn",
        "gp",
        "fortnight",
        "monsoon",
        "abandonment",
        "everyone",
        "corner",
        "lake",
        "samei",
        "lap",
        "achievement",
        "home",
        "podium",
        "bullsthis",
        "script",
        "f1",
        "circus",
        "week",
        "australia",
        "malaysia",
        "doublediffuser",
        "device",
        "rear",
        "fia",
        "dominance",
        "barrichello",
        "credit",
        "newey",
        "sport",
        "landmark",
        "restraint",
        "fan",
        "monty",
        "python",
        "beatlesthey",
        "michael",
        "meister",
        "man",
        "baby",
        "schumi",
        "monza",
        "victor",
        "history",
        "toro",
        "rosso",
        "rainhorner",
        "greatness",
        "world",
        "champion",
        "sit"
    ],
    "category": [
        "sport",
        "formulaone"
    ]
}