{
    "title": "Body dredged up from River Avon 'is clubber who disappeared a month ago'",
    "url": "https://www.dailymail.co.uk/news/article-1238697/Body-dredged-River-Avon-clubber-disappeared-month-ago.html",
    "date": "2009-12-27",
    "keywords": [
        "flagg",
        "river",
        "body",
        "month",
        "bath",
        "avon",
        "mail",
        "reporter",
        "gmt",
        "december",
        "view",
        "nightclubber",
        "police",
        "cctv",
        "city",
        "car",
        "park",
        "mewstheir",
        "search",
        "water",
        "yesterday",
        "locksbrook",
        "sluice",
        "sergeant",
        "peter",
        "knight",
        "today",
        "person",
        "identification",
        "post",
        "mortem",
        "community",
        "support",
        "everyone",
        "searchessince",
        "mr",
        "family",
        "campaign",
        "region",
        "vigil",
        "walk",
        "facebook",
        "group",
        "radstock",
        "spa",
        "university",
        "degree",
        "design",
        "playground",
        "equipment",
        "designer",
        "playforce",
        "melksham",
        "wiltshirehe",
        "derek",
        "marian",
        "son",
        "disappearance",
        "home"
    ],
    "category": [
        "news"
    ]
}