{
    "title": "Will I have to repay inheritance?",
    "url": "https://www.dailymail.co.uk/money/experts/article-1679812/Will-I-have-to-repay-inheritance.html",
    "date": "2009-08-27",
    "keywords": [
        "estate",
        "iht",
        "inheritance",
        "tax",
        "liability",
        "share",
        "amount",
        "charity",
        "advice",
        "money",
        "gmt",
        "view",
        "friend",
        "worth",
        "june",
        "aspect",
        "beneficiary",
        "knowledge",
        "jd",
        "glasgow",
        "mark",
        "butterworth",
        "skipton",
        "gift",
        "deduction",
        "family",
        "portion",
        "figure",
        "band",
        "calculation",
        "charge",
        "matter",
        "area",
        "point",
        "guidance",
        "contact",
        "information",
        "centre"
    ],
    "category": [
        "money",
        "experts"
    ]
}