{
    "title": "Matt Denny gets it right at Sydney Classic",
    "url": "https://www.dailymail.co.uk/wires/aap/article-10605695/Matt-Denny-gets-right-Sydney-Classic.html",
    "date": "2022-03-12",
    "keywords": [
        "denny",
        "meet",
        "olympic",
        "record",
        "sydney",
        "time",
        "queenslander",
        "matt",
        "night",
        "aap",
        "lot",
        "bol",
        "zealander",
        "clay",
        "runner",
        "discus",
        "finalist",
        "fate",
        "man",
        "track",
        "tokyo",
        "bronze",
        "medal",
        "round",
        "park",
        "centre",
        "throw",
        "didnt",
        "word",
        "gear",
        "told",
        "miss",
        "brain",
        "kind",
        "youre",
        "thing",
        "everything",
        "nothing",
        "home",
        "quarantine",
        "process",
        "person",
        "place",
        "finisher",
        "star",
        "peter",
        "event",
        "appearance",
        "metre",
        "world",
        "belgrade",
        "win",
        "distance",
        "pressure",
        "havent",
        "run",
        "opportunity",
        "race",
        "beck",
        "form",
        "ella",
        "claudia",
        "hollingsworth",
        "jude",
        "thomas",
        "cameron",
        "griffith",
        "title",
        "eddie",
        "oseinketia",
        "jack",
        "hale"
    ],
    "category": [
        "wires",
        "aap"
    ]
}