{
    "title": "Grenfell Tower: Fire brigade interviewed by police",
    "url": "http://www.bbc.co.uk/news/uk-49718573",
    "date": "2019-09-16",
    "keywords": [
        "fire",
        "grenfell",
        "inquiry",
        "tower",
        "brigade",
        "police",
        "interview",
        "health",
        "safety",
        "june",
        "london",
        "service",
        "work",
        "cotton",
        "guarantee",
        "emergency",
        "manslaughter",
        "september",
        "panelshare",
        "pagecopy",
        "linkabout",
        "sharingimage",
        "source",
        "caution",
        "body",
        "relation",
        "act",
        "commissioner",
        "staff",
        "investigatorswe",
        "group",
        "questionsit",
        "madethe",
        "met",
        "use",
        "stay",
        "policy",
        "line",
        "actthe",
        "law",
        "risksin",
        "statement",
        "lfb",
        "public",
        "accordance",
        "phase",
        "year",
        "decision",
        "wider",
        "offencesin",
        "force",
        "community",
        "family",
        "firepublished14",
        "chargespublished10",
        "report",
        "delayedpublished17",
        "victimspublished30"
    ],
    "category": [
        "news",
        "uk"
    ]
}