{
    "title": "Western Australia: Isolated state reopens two years into the pandemic",
    "url": "http://www.bbc.co.uk/news/world-australia-60582788",
    "date": "2022-03-03",
    "keywords": [
        "state",
        "video",
        "australia",
        "policy",
        "country",
        "border",
        "march",
        "play",
        "javascript",
        "caption",
        "travel",
        "mcgowan",
        "month",
        "player",
        "rush",
        "arrival",
        "case",
        "lockdown",
        "pandemicpublished3",
        "panelshare",
        "pagecopy",
        "watch",
        "\u00e2hermit",
        "kingdom\u00e2",
        "coronavirus",
        "pandemicthe",
        "entry",
        "city",
        "sydney",
        "travelwestern",
        "virus",
        "spreadingbut",
        "countrythe",
        "hermit",
        "kingdom",
        "hardline",
        "mark",
        "dictator",
        "kim",
        "jongun",
        "boss",
        "airline",
        "alan",
        "joyce",
        "day",
        "reunionaustralia",
        "covidcelebrity",
        "antigen",
        "test",
        "world",
        "onset",
        "covid",
        "nation",
        "victoria",
        "caseswestern",
        "half",
        "pandemic",
        "delta",
        "move",
        "nearzero",
        "ratepremier",
        "success",
        "pandemicyou",
        "browsermedia",
        "queensland",
        "couple",
        "dying",
        "father",
        "yearmore",
        "storyaustralia",
        "covidpublished3",
        "standardpublished1",
        "battle",
        "australiapublished26"
    ],
    "category": [
        "news",
        "world-australia"
    ]
}