{
    "title": "Erdogan's party pivots back to orthodox economic policies in draft manifesto -sources",
    "url": "https://www.dailymail.co.uk/wires/reuters/article-11869747/Erdogans-party-pivots-orthodox-economic-policies-draft-manifesto-sources.html",
    "date": "2023-03-16",
    "keywords": [
        "economy",
        "simsek",
        "manifesto",
        "turkey",
        "election",
        "party",
        "market",
        "inflation",
        "minister",
        "akp",
        "draft",
        "president",
        "policy",
        "rate",
        "approach",
        "ak",
        "official",
        "alliance",
        "coskun",
        "opinion",
        "erdogan",
        "challenge",
        "model",
        "interest",
        "reference",
        "deputy",
        "government",
        "issue",
        "cabinet",
        "opposition",
        "deficit",
        "march",
        "return",
        "matter",
        "power",
        "popularity",
        "erosion",
        "living",
        "depreciation",
        "lira",
        "time",
        "ankara",
        "cycle",
        "face",
        "trend",
        "borrowing",
        "bank",
        "benchmark",
        "basis",
        "energy",
        "food",
        "invasion",
        "ukraine",
        "year",
        "earthquake",
        "feb",
        "damage",
        "partys",
        "subject",
        "role",
        "finance",
        "october",
        "series",
        "crash",
        "currency",
        "hand",
        "forex",
        "work",
        "stage",
        "sign",
        "kind",
        "nonmarket",
        "comment",
        "pivot",
        "blaise",
        "antin",
        "head",
        "research",
        "asset",
        "manager",
        "tcw",
        "news",
        "caution",
        "past",
        "skepticism",
        "accountability",
        "public",
        "sector",
        "transparency",
        "approval",
        "management",
        "appointment",
        "success",
        "office",
        "change",
        "bureaucracy",
        "harmony",
        "source",
        "knowledge",
        "share"
    ],
    "category": [
        "wires",
        "reuters"
    ]
}