{
    "title": "UK stocks decline for second day on BoE rate hike worries",
    "url": "https://www.dailymail.co.uk/wires/reuters/article-12123303/UK-stocks-tumble-second-day-BoE-rate-hike-worries.html",
    "date": "2023-05-25",
    "keywords": [
        "energy",
        "boe",
        "home",
        "johnson",
        "market",
        "johann",
        "cherian",
        "shashwat",
        "chauhan",
        "oil",
        "inflation",
        "meeting",
        "estate",
        "debt",
        "fy",
        "mining",
        "commodity",
        "analyst",
        "paragraph",
        "thursday",
        "tightening",
        "bank",
        "england",
        "bluechip",
        "briefly",
        "eightweek",
        "wednesday",
        "hawkish",
        "theyre",
        "bit",
        "concern",
        "emea",
        "strategist",
        "bny",
        "mellon",
        "interest",
        "uncertainty",
        "rate",
        "hike",
        "remain",
        "investment",
        "sector",
        "minister",
        "production",
        "week",
        "metal",
        "gold",
        "pet",
        "care",
        "firm",
        "matthey",
        "autocatalyst",
        "maker",
        "profit",
        "cineworld",
        "cinema",
        "chain",
        "operator",
        "bankruptcy",
        "protection",
        "trend",
        "carnival",
        "citigroup",
        "cruise",
        "rating",
        "hold",
        "rangebound",
        "april",
        "deal",
        "sentiment",
        "ceiling",
        "june",
        "deadline",
        "risk",
        "economy",
        "reporting",
        "bengaluru",
        "editing",
        "sonia",
        "cheema",
        "rashmi",
        "aich"
    ],
    "category": [
        "wires",
        "reuters"
    ]
}