{
    "title": "Experts demand a new approach to head injuries after Alex Greenwood's sickening knock against Brazil saw the Lionesses hero forced to withdraw after showing symptoms of concussion",
    "url": "https://www.dailymail.co.uk/sport/football/article-11977219/Concussion-experts-demand-new-approach-head-injuries-Alex-Greenwoods-sickening-knock.html",
    "date": "2023-04-15",
    "keywords": [
        "concussion",
        "head",
        "research",
        "game",
        "injury",
        "sport",
        "greenwood",
        "risk",
        "football",
        "brain",
        "week",
        "manchester",
        "university",
        "dementia",
        "player",
        "sutton",
        "practice",
        "guidance",
        "turf",
        "star",
        "day",
        "decision",
        "mail",
        "columnist",
        "mike",
        "battle",
        "introduction",
        "thing",
        "fa",
        "tottenham",
        "manager",
        "espirito",
        "santo",
        "ball",
        "impact",
        "brazilgreenwood",
        "minute",
        "finalissima",
        "wembley",
        "treatment",
        "defender",
        "taking",
        "penalty",
        "shootoutbut",
        "city",
        "glasgow",
        "disease",
        "lifethey",
        "england",
        "challenge",
        "brazil",
        "header",
        "pitch",
        "criticism",
        "charity",
        "headway",
        "lie",
        "motionless",
        "ground",
        "moment",
        "argument",
        "blow",
        "team",
        "association",
        "board",
        "ifab",
        "trial",
        "potential",
        "field",
        "premier",
        "league",
        "example",
        "introducednobody",
        "damage",
        "world",
        "father",
        "substitutesit",
        "substitute",
        "sanctuary",
        "room",
        "doctor",
        "look",
        "disadvantage",
        "everybody",
        "itlove",
        "campaign",
        "staff",
        "sporting",
        "substitution",
        "interventionthe",
        "evidence",
        "truth",
        "clubs",
        "higherforce",
        "season",
        "reality",
        "method",
        "heading",
        "technique",
        "footballwest"
    ],
    "category": [
        "sport",
        "football"
    ]
}