{
    "title": "Johnny Vaughan, 54, makes a low-key exit from his radio duties in London after welcoming baby son Milton during lockdown with partner Vanessa Howard, 36",
    "url": "https://www.dailymail.co.uk/tvshowbiz/article-8836367/Johnny-Vaughan-54-makes-low-key-exit-radio-duties-London-welcoming-son-Milton.html",
    "date": "2020-10-13",
    "keywords": [
        "johnny",
        "milton",
        "july",
        "radio",
        "vanessa",
        "partner",
        "father",
        "marriage",
        "son",
        "vaughan",
        "dj",
        "share",
        "month",
        "time",
        "howard",
        "appearance",
        "leicester",
        "square",
        "london",
        "breakfast",
        "star",
        "rain",
        "jacket",
        "baby",
        "holiday",
        "pregnancy",
        "world",
        "chelsea",
        "westminster",
        "hospital",
        "staff",
        "delivery",
        "breakdown",
        "couple",
        "pregnancyand",
        "tuesdaythe",
        "home",
        "lowkey",
        "phone",
        "call",
        "capitalsince",
        "instagram",
        "kate",
        "garraway",
        "beams",
        "bundle",
        "article",
        "picture",
        "tot",
        "tv",
        "august",
        "family",
        "become",
        "beach",
        "snap",
        "sardinia",
        "sun",
        "tan",
        "caladivolpejohnny",
        "adult",
        "boy",
        "presenter",
        "child",
        "girlfriend",
        "instagramhe",
        "news",
        "bed",
        "newborn",
        "wow",
        "dad",
        "birth",
        "split",
        "wife",
        "age",
        "jaunt",
        "rice",
        "skiing",
        "trip"
    ],
    "category": [
        "tvshowbiz"
    ]
}