{
    "title": "'Detach yourself from emotion': What internet opportunist told Mitch Winehouse after taking charity web address for Amy",
    "url": "https://www.dailymail.co.uk/tvshowbiz/article-2028814/Amy-Winehouse-dead-Father-Mitch-forced-foundation-donations.html",
    "date": "2011-08-22",
    "keywords": [
        "foundation",
        "mitch",
        "winehouse",
        "name",
        "mccann",
        "death",
        "opportunist",
        "charity",
        "domain",
        "daughter",
        "hold",
        "im",
        "help",
        "detach",
        "web",
        "address",
        "amys",
        "anything",
        "business",
        "amy",
        "bank",
        "blake",
        "keith",
        "vaz",
        "mp",
        "internet",
        "july",
        "emotion",
        "fitzmaurice",
        "mendoza",
        "gmt",
        "august",
        "view",
        "martin",
        "mccannjust",
        "drug",
        "uxbridge",
        "resident",
        "someone",
        "sun",
        "ltd",
        "house",
        "result",
        "account",
        "situationon",
        "anger",
        "pressure",
        "nameinstead",
        "funding",
        "havent",
        "ac",
        "siche",
        "person",
        "website",
        "withdrawnmitch",
        "exhusband",
        "fieldercivil",
        "parliament",
        "anybody",
        "click",
        "mouse",
        "effort",
        "world",
        "service",
        "provider",
        "hand",
        "arrangement",
        "twitter",
        "possession",
        "shock",
        "month",
        "individual",
        "cash",
        "evidence",
        "user",
        "sghuk",
        "cheshire",
        "amywinehousefoundationorguk",
        "meanwhile",
        "amywinehousefoundationcom",
        "amywinehousefoundationorg",
        "guardian",
        "drink",
        "project",
        "daughtersspeaking",
        "cousin",
        "michael",
        "heard",
        "something",
        "substance",
        "abusein",
        "country",
        "rehabilitation",
        "clinic",
        "list",
        "home",
        "camden",
        "toxicology",
        "situation",
        "night"
    ],
    "category": [
        "tvshowbiz"
    ]
}