{
    "title": "Cambodian opposition leader arrested for alleged 'treason'",
    "url": "https://www.dailymail.co.uk/wires/afp/article-4847378/Cambodian-opposition-leader-arrested-alleged-treason.html",
    "date": "2017-09-02",
    "keywords": [
        "kem",
        "leader",
        "government",
        "opposition",
        "court",
        "sokha",
        "statement",
        "hun",
        "party",
        "cnrp",
        "treason",
        "sen",
        "conspiracy",
        "july",
        "sunday",
        "flurry",
        "strongman",
        "premier",
        "surprise",
        "arrest",
        "press",
        "election",
        "year",
        "decade",
        "rule",
        "popularity",
        "rescue",
        "plan",
        "group",
        "secret",
        "act",
        "crime",
        "warrant",
        "home",
        "daughter",
        "monovithya",
        "twitter",
        "post",
        "saturday",
        "night",
        "progovernment",
        "website",
        "news",
        "support",
        "evidence",
        "claim",
        "week",
        "concern",
        "state",
        "cambodias",
        "democracy",
        "ngo",
        "crackdown",
        "firing",
        "line",
        "closure",
        "monday",
        "tax",
        "bill",
        "threat",
        "move",
        "reporting"
    ],
    "category": [
        "wires",
        "afp"
    ]
}