{
    "title": "President Trump's Scottish resorts' losses doubled in the last year as his bid to host the coveted Scottish Open is in doubt with a major sponsor citing concerns over his 'politics'",
    "url": "https://www.dailymail.co.uk/news/article-4959042/Trump-s-Scottish-resorts-losses-doubled-past-year.html",
    "date": "2017-10-07",
    "keywords": [
        "trump",
        "resort",
        "golf",
        "company",
        "course",
        "scotland",
        "turnberry",
        "report",
        "june",
        "sea",
        "government",
        "year",
        "bid",
        "donald",
        "business",
        "open",
        "doubt",
        "president",
        "management",
        "group",
        "friday",
        "revenue",
        "sponsor",
        "club",
        "helicopter",
        "ceo",
        "decision",
        "asset",
        "martin",
        "share",
        "court",
        "farm",
        "august",
        "ivanka",
        "petition",
        "watchdog",
        "son",
        "couple",
        "house",
        "coursesin",
        "refurbishment",
        "bagpipe",
        "player",
        "dress",
        "nominee",
        "july",
        "newspaper",
        "gilbert",
        "venue",
        "clarification",
        "meant",
        "spokesman",
        "thorneley",
        "kind",
        "right",
        "dozen",
        "way",
        "development",
        "manager",
        "obama",
        "energy",
        "summit",
        "coding",
        "article",
        "fight",
        "offshore",
        "windmill",
        "building",
        "risk",
        "coursesamanda",
        "miller",
        "spokeswoman",
        "organization",
        "resultstrump",
        "adult",
        "interest",
        "role",
        "trumps",
        "addition",
        "loss",
        "value",
        "pound",
        "cent",
        "ribbon",
        "tee",
        "family",
        "junior",
        "granddaughter",
        "mr",
        "undergone",
        "month",
        "buying",
        "wager",
        "industry",
        "bit",
        "departure",
        "name",
        "marketing",
        "fee",
        "himselfmuch"
    ],
    "category": [
        "news"
    ]
}