{
    "title": "Veterans launch 'Gulf War Syndrome' inquiry",
    "url": "https://www.dailymail.co.uk/health/article-306537/Veterans-launch-Gulf-War-Syndrome-inquiry.html",
    "date": "2004-06-14",
    "keywords": [
        "war",
        "inquiry",
        "syndrome",
        "lloyd",
        "britain",
        "probe",
        "cocktail",
        "jabs",
        "preparation",
        "variety",
        "conflictthe",
        "judge",
        "lord",
        "berwick",
        "health",
        "conflict",
        "iraq",
        "government",
        "pressure",
        "investigation",
        "issue",
        "deploymentindependent",
        "probehowever",
        "legion",
        "charity",
        "probei",
        "intention",
        "statementhis",
        "diedgulf",
        "mystery",
        "ministry",
        "defence",
        "public",
        "range",
        "problem",
        "adviser"
    ],
    "category": [
        "health"
    ]
}