{
    "title": "It's Peel day - small but in a big way",
    "url": "https://www.dailymail.co.uk/tvshowbiz/article-365260/Its-Peel-day--small-big-way.html",
    "date": "2005-10-13",
    "keywords": [
        "john",
        "music",
        "day",
        "show",
        "concert",
        "radio",
        "order",
        "legacy",
        "today",
        "ukthe",
        "peel",
        "anniversary",
        "celebration",
        "life",
        "contribution",
        "dj",
        "dedication",
        "october",
        "year",
        "heart",
        "attack",
        "holiday",
        "peruat",
        "size",
        "pubs",
        "kind",
        "spain",
        "germany",
        "zealand",
        "canadadedicationbbc",
        "output",
        "hour",
        "djs",
        "musicroger",
        "daltrey",
        "elton",
        "robert",
        "plant",
        "gilmour",
        "shelley",
        "tribute",
        "brainchild",
        "night",
        "london",
        "fall",
        "furry",
        "front",
        "bernard",
        "sumner",
        "crowd",
        "band",
        "support",
        "incarnation",
        "joy",
        "division"
    ],
    "category": [
        "tvshowbiz"
    ]
}