{
    "title": "Illegal GM rice found in 10 per cent of UK samples",
    "url": "https://www.dailymail.co.uk/news/article-416853/Illegal-GM-rice-10-cent-UK-samples.html",
    "date": "2006-11-16",
    "keywords": [
        "rice",
        "gm",
        "material",
        "food",
        "safety",
        "grain",
        "watchdog",
        "fsa",
        "eu",
        "law",
        "risk",
        "advice",
        "cent",
        "agency",
        "levelsthe",
        "content",
        "home",
        "saidin",
        "emergency",
        "strainsin",
        "addition",
        "point",
        "entry",
        "area",
        "fsas",
        "requestmost",
        "period",
        "sample",
        "findingsa",
        "spokesman",
        "presence",
        "levelshowever",
        "basis",
        "evidence",
        "trace",
        "concernthe",
        "month",
        "shelvesthe",
        "authority",
        "concernbut",
        "information",
        "assessment",
        "issue"
    ],
    "category": [
        "news"
    ]
}