{
    "title": "Why those holiday mozzies really DO prefer biting women: Is it only because we bare more flesh, or are there other factors?",
    "url": "https://www.dailymail.co.uk/femail/article-2386261/Why-holiday-mosquitoes-really-DO-prefer-biting-women.html",
    "date": "2013-08-07",
    "keywords": [
        "skin",
        "body",
        "mosquito",
        "blood",
        "carbon",
        "study",
        "reason",
        "world",
        "temperature",
        "smell",
        "acid",
        "beer",
        "group",
        "britain",
        "time",
        "energy",
        "dr",
        "journal",
        "odour",
        "gmt",
        "august",
        "thing",
        "handful",
        "feed",
        "share",
        "sex",
        "myth",
        "range",
        "gas",
        "organ",
        "dioxide",
        "prone",
        "sweat",
        "sweaty",
        "logan",
        "alcohol",
        "bite",
        "response",
        "holiday",
        "timeby",
        "david",
        "derbyshire",
        "mailonline",
        "email",
        "view",
        "rain",
        "water",
        "season",
        "nectar",
        "order",
        "boost",
        "humansin",
        "fever",
        "loneliness",
        "regret",
        "woman",
        "childless",
        "liar",
        "shame",
        "rot",
        "article",
        "bloody",
        "meal",
        "tribe",
        "dioxidefemale",
        "presence",
        "odourless",
        "palp",
        "source",
        "moving",
        "fuel",
        "byproduct",
        "food",
        "metabolic",
        "evidence",
        "fat",
        "risk",
        "expert",
        "host",
        "strategy",
        "area",
        "workout",
        "humanthe",
        "school",
        "hygiene",
        "medicine",
        "moisture",
        "sense",
        "air",
        "pair",
        "feathery",
        "antennae",
        "exercise",
        "chemical",
        "octenol",
        "breath",
        "youre",
        "produce",
        "mozziessome",
        "workoutpregnancy"
    ],
    "category": [
        "femail"
    ]
}