{
    "title": "RIATH AL-SAMARRAI: Tears of a child and the fury of her rivals with Kamila Valieva set for gold despite failed drugs test... USA hit out at 'dirty cheaters and child abusers' and one of the biggest scandals in Olympic history is likely to be get far bigger",
    "url": "https://www.dailymail.co.uk/sport/sportsnews/article-10516603/RIATH-AL-SAMARRAI-Valieva-set-gold-USA-hit-dirty-cheaters-child-abusers.html",
    "date": "2022-02-15",
    "keywords": [
        "valieva",
        "russia",
        "fury",
        "share",
        "figure",
        "team",
        "skater",
        "perfect",
        "kamila",
        "martin",
        "samuel",
        "winter",
        "drug",
        "cheat",
        "world",
        "article",
        "tuesday",
        "programme",
        "score",
        "footing",
        "triple",
        "close",
        "reason",
        "ice",
        "heart",
        "medication",
        "something",
        "play",
        "row",
        "tutberidze",
        "fall",
        "child",
        "prodigy",
        "cloud",
        "week",
        "fog",
        "sanction",
        "title",
        "crown",
        "leaderboard",
        "program",
        "night",
        "season",
        "lead",
        "skate",
        "teammate",
        "anna",
        "performance",
        "life",
        "folk",
        "wept",
        "cause",
        "girl",
        "tuesdayit",
        "fact",
        "christmas",
        "court",
        "reprieve",
        "face",
        "tuesdaysomewhere",
        "accident",
        "temptation",
        "victim",
        "lust",
        "luck",
        "drinking",
        "glass",
        "grandfather",
        "possibility",
        "defence",
        "lawyer",
        "mondayit",
        "anger",
        "rant",
        "rippon",
        "gold",
        "dirty",
        "alexandra",
        "part",
        "silence",
        "briefly",
        "television",
        "morning",
        "fatigue",
        "zone",
        "victory",
        "press",
        "conference",
        "controversy",
        "one",
        "way",
        "start",
        "medal",
        "ceremony",
        "momentso",
        "mind",
        "theme",
        "interview",
        "area",
        "josefin"
    ],
    "category": [
        "sport",
        "sportsnews"
    ]
}